textual_coloromatic/__init__.py
textual_coloromatic/art_loader.py
textual_coloromatic/coloromatic.py
textual_coloromatic/help.md
textual_coloromatic/py.typed
textual_coloromatic/demo/__init__.py
textual_coloromatic/demo/datawidget.py
textual_coloromatic/demo/main.py
textual_coloromatic/demo/screens.py
textual_coloromatic/demo/settingsbar.py
textual_coloromatic/demo/styles.tcss
textual_coloromatic/demo/validators.py
textual_coloromatic/demo/demo_art/abstract1.txt
textual_coloromatic/demo/demo_art/arch.txt
textual_coloromatic/demo/demo_art/celtic_knot1.txt
textual_coloromatic/demo/demo_art/celtic_knot2.txt
textual_coloromatic/demo/demo_art/flowsnake3.txt
textual_coloromatic/demo/demo_art/impossible_triangle.txt
textual_coloromatic/demo/demo_art/mountains1.txt
textual_coloromatic/demo/demo_art/sierpinsky_gasket.txt
textual_coloromatic/patterns/brick1.txt
textual_coloromatic/patterns/brick2.txt
textual_coloromatic/patterns/crosses.txt
textual_coloromatic/patterns/fence1.txt
textual_coloromatic/patterns/fence2.txt
textual_coloromatic/patterns/fish.txt
textual_coloromatic/patterns/hive.txt
textual_coloromatic/patterns/honeycomb1.txt
textual_coloromatic/patterns/honeycomb2.txt
textual_coloromatic/patterns/honeycomb3.txt
textual_coloromatic/patterns/jaggedwave.txt
textual_coloromatic/patterns/persian.txt
textual_coloromatic/patterns/squares.txt
textual_coloromatic/patterns/tesselation1.txt
textual_coloromatic/patterns/tesselation2.txt
textual_coloromatic/patterns/tesselation3.txt
textual_coloromatic/patterns/triangles.txt
textual_coloromatic/patterns/weave.txt
textual_coloromatic-1.0.1.dist-info/METADATA
textual_coloromatic-1.0.1.dist-info/WHEEL
textual_coloromatic-1.0.1.dist-info/entry_points.txt
textual_coloromatic-1.0.1.dist-info/RECORD
