Metadata-Version: 2.4
Name: textual-coloromatic
Version: 1.0.1
Summary: A Textual widget for displaying ASCII art with color effects and animations.
Project-URL: Repository, https://github.com/edward-jazzhands/textual-coloromatic
Project-URL: Changelog, https://github.com/edward-jazzhands/textual-coloromatic/blob/master/CHANGELOG.md
License: MIT
Keywords: art,ascii,color,coloromatic,python,textual,tui,widget
Classifier: Development Status :: 5 - Production/Stable
Classifier: License :: OSI Approved :: MIT License
Classifier: Operating System :: OS Independent
Classifier: Programming Language :: Python
Classifier: Programming Language :: Python :: 3 :: Only
Classifier: Programming Language :: Python :: 3.9
Classifier: Programming Language :: Python :: 3.10
Classifier: Programming Language :: Python :: 3.11
Classifier: Programming Language :: Python :: 3.12
Classifier: Programming Language :: Python :: 3.13
Requires-Python: >=3.9
Requires-Dist: textual-slidecontainer>=1.0.0
Requires-Dist: textual<6.0.0,>=3.0.0
